Moral88/__init__.py
Moral88/classification.py
Moral88/clustering.py
Moral88/regression.py
Moral88/utils.py
Test/__init__.py
Test/test_classification.py
Test/test_clustering.py
Test/test_regression.py
Moral88-0.13.0.dist-info/LICENSE
Moral88-0.13.0.dist-info/METADATA
Moral88-0.13.0.dist-info/WHEEL
Moral88-0.13.0.dist-info/top_level.txt
Moral88-0.13.0.dist-info/RECORD
